django_custom_error_views/__init__.py
django_custom_error_views/apps.py
django_custom_error_views/static/django_custom_error_views/input.css
django_custom_error_views/static/django_custom_error_views/output.css
django_custom_error_views/static/django_custom_error_views/visual-400.jpg
django_custom_error_views/static/django_custom_error_views/visual-403.jpg
django_custom_error_views/static/django_custom_error_views/visual-404.jpg
django_custom_error_views/static/django_custom_error_views/visual-500.jpg
django_custom_error_views/templates/400.html
django_custom_error_views/templates/403.html
django_custom_error_views/templates/404.html
django_custom_error_views/templates/410.html
django_custom_error_views/templates/500.html
django_custom_error_views/templates/django_custom_error_views/base.html
django_custom_error_views/views.py
django_custom_error_views-0.2.5.dist-info/LICENSE
django_custom_error_views-0.2.5.dist-info/METADATA
django_custom_error_views-0.2.5.dist-info/WHEEL
django_custom_error_views-0.2.5.dist-info/RECORD
